Metadata-Version: 2.0
Name: odoo9-addon-auth-supplier
Version: 9.0.2.0.0.99.dev15
Summary: Auth Supplier
Home-page: http://www.incaser.es
Author: Antiun Ingeniería S.L., Incaser Informatica S.L., Tecnativa, Odoo Community Association (OCA)
Author-email: support@odoo-community.org
License: AGPL-3
Platform: UNKNOWN
Classifier: Programming Language :: Python
Classifier: Framework :: Odoo
Classifier: License :: OSI Approved :: GNU Affero General Public License v3
Requires-Python: ~=2.7
Requires-Dist: odoo (<9.1a,>=9.0a)
